{"_type":"export","__export_format":4,"__export_date":"2021-06-26T18:31:01.621Z","__export_source":"insomnia.desktop.app:v2021.1.0","resources":[{"_id":"req_3aca80c9a96b4c0491c7da795360b0a5","parentId":"fld_f6090b7a311d436695b85597cc7287a2","modified":1624716213309,"created":1624715444322,"url":"http://127.0.0.1:8000/order","name":"List Orders","description":"","method":"GET","body":{},"parameters":[],"headers":[],"authentication":{},"metaSortKey":-1624715449682,"isPrivate":false,"settingStoreCookies":true,"settingSendCookies":true,"settingDisableRenderRequestBody":false,"settingEncodeUrl":true,"settingRebuildPath":true,"settingFollowRedirects":"global","_type":"request"},{"_id":"fld_f6090b7a311d436695b85597cc7287a2","parentId":"wrk_9a02bb9cbdc244628a679b016925eb11","modified":1624716200894,"created":1624716200894,"name":"Order","description":"","environment":{},"environmentPropertyOrder":null,"metaSortKey":-1624716200895,"_type":"request_group"},{"_id":"wrk_9a02bb9cbdc244628a679b016925eb11","parentId":null,"modified":1624715432655,"created":1624715432655,"name":"Mozantech","description":"","scope":"collection","_type":"workspace"},{"_id":"req_697f655689ed49cab0e573049bc64512","parentId":"fld_f6090b7a311d436695b85597cc7287a2","modified":1624724088255,"created":1624716148951,"url":"http://127.0.0.1:8000/order/2","name":"Show Order","description":"","method":"GET","body":{},"parameters":[],"headers":[],"authentication":{},"metaSortKey":-1624715449669.5,"isPrivate":false,"settingStoreCookies":true,"settingSendCookies":true,"settingDisableRenderRequestBody":false,"settingEncodeUrl":true,"settingRebuildPath":true,"settingFollowRedirects":"global","_type":"request"},{"_id":"req_941230fd2c574b31a78d433cd205577f","parentId":"fld_f6090b7a311d436695b85597cc7287a2","modified":1624731118538,"created":1624731099417,"url":"http://127.0.0.1:8000/order/2/pay","name":"Pay Order","description":"","method":"PUT","body":{},"parameters":[],"headers":[],"authentication":{},"metaSortKey":-1624715449663.25,"isPrivate":false,"settingStoreCookies":true,"settingSendCookies":true,"settingDisableRenderRequestBody":false,"settingEncodeUrl":true,"settingRebuildPath":true,"settingFollowRedirects":"global","_type":"request"},{"_id":"req_e40b5fc13e2b4fe7965039e19c9372b7","parentId":"fld_f6090b7a311d436695b85597cc7287a2","modified":1624731588510,"created":1624715449432,"url":"http://127.0.0.1:8000/order","name":"Create Order","description":"","method":"POST","body":{"mimeType":"application/json","text":"{\n\t\"products\": [4,2],\n\t\"paymentMethod\": 2\n}\t "},"parameters":[],"headers":[{"name":"Content-Type","value":"application/json","id":"pair_e7625222ad9e4d1a9a8f6abc8e3f7a0a"}],"authentication":{},"metaSortKey":-1624715449657,"isPrivate":false,"settingStoreCookies":true,"settingSendCookies":true,"settingDisableRenderRequestBody":false,"settingEncodeUrl":true,"settingRebuildPath":true,"settingFollowRedirects":"global","_type":"request"},{"_id":"req_17bd4dee49e9483d8e6bdebd3904f1d5","parentId":"fld_1ef8c921ff9c478f85fd1bfe69490f41","modified":1624731457947,"created":1624731176950,"url":"http://127.0.0.1:8000/payment-method","name":"Create Payment Method","description":"","method":"POST","body":{"mimeType":"application/json","text":"{\n\t\"name\": \"test\"\n}"},"parameters":[],"headers":[{"name":"Content-Type","value":"application/json","id":"pair_34554087d46e4db487032a513d4ff1ce"}],"authentication":{},"metaSortKey":-1624731176989,"isPrivate":false,"settingStoreCookies":true,"settingSendCookies":true,"settingDisableRenderRequestBody":false,"settingEncodeUrl":true,"settingRebuildPath":true,"settingFollowRedirects":"global","_type":"request"},{"_id":"fld_1ef8c921ff9c478f85fd1bfe69490f41","parentId":"wrk_9a02bb9cbdc244628a679b016925eb11","modified":1624731170608,"created":1624731165401,"name":"Payment Method","description":"","environment":{},"environmentPropertyOrder":null,"metaSortKey":-1624716200870,"_type":"request_group"},{"_id":"req_d9642f08340a404688b51d0372615885","parentId":"fld_1ef8c921ff9c478f85fd1bfe69490f41","modified":1624731473709,"created":1624731465043,"url":"http://127.0.0.1:8000/payment-method","name":"List Payment Methods","description":"","method":"GET","body":{},"parameters":[],"headers":[],"authentication":{},"metaSortKey":-1624730424493.5,"isPrivate":false,"settingStoreCookies":true,"settingSendCookies":true,"settingDisableRenderRequestBody":false,"settingEncodeUrl":true,"settingRebuildPath":true,"settingFollowRedirects":"global","_type":"request"},{"_id":"req_feea2b51042241939a29c3476039608d","parentId":"fld_1ef8c921ff9c478f85fd1bfe69490f41","modified":1624731540797,"created":1624731538686,"url":"http://127.0.0.1:8000/payment-method/2","name":"Show Payment Method","description":"","method":"GET","body":{},"parameters":[],"headers":[],"authentication":{},"metaSortKey":-1624730048245.75,"isPrivate":false,"settingStoreCookies":true,"settingSendCookies":true,"settingDisableRenderRequestBody":false,"settingEncodeUrl":true,"settingRebuildPath":true,"settingFollowRedirects":"global","_type":"request"},{"_id":"req_05f68cf47f564d28b46f1bb79238b4e4","parentId":"fld_e21dc3fb9cbf4ee383b43bb32ded8615","modified":1624730848237,"created":1624729671998,"url":"http://127.0.0.1:8000/product","name":"Create Product","description":"","method":"GET","body":{},"parameters":[],"headers":[],"authentication":{},"metaSortKey":-1624729671998,"isPrivate":false,"settingStoreCookies":true,"settingSendCookies":true,"settingDisableRenderRequestBody":false,"settingEncodeUrl":true,"settingRebuildPath":true,"settingFollowRedirects":"global","_type":"request"},{"_id":"fld_e21dc3fb9cbf4ee383b43bb32ded8615","parentId":"wrk_9a02bb9cbdc244628a679b016925eb11","modified":1624716381427,"created":1624716377062,"name":"Product","description":"","environment":{},"environmentPropertyOrder":null,"metaSortKey":-1624716200845,"_type":"request_group"},{"_id":"req_c3e38cd9c8d8496599d05366044d5512","parentId":"fld_e21dc3fb9cbf4ee383b43bb32ded8615","modified":1624730908603,"created":1624730865705,"url":"http://127.0.0.1:8000/product","name":"Create Product","description":"","method":"POST","body":{"mimeType":"application/json","text":"{\n\t\"name\": \"Produto Teste\",\n\t\"price\": 100\n}"},"parameters":[],"headers":[{"name":"Content-Type","value":"application/json","id":"pair_e0eb724625ec40e9a565faca484dbcfd"}],"authentication":{},"metaSortKey":-1624722560840,"isPrivate":false,"settingStoreCookies":true,"settingSendCookies":true,"settingDisableRenderRequestBody":false,"settingEncodeUrl":true,"settingRebuildPath":true,"settingFollowRedirects":"global","_type":"request"},{"_id":"req_1ccd60b06be74873b26e25c463784733","parentId":"fld_e21dc3fb9cbf4ee383b43bb32ded8615","modified":1624730948838,"created":1624730935625,"url":"http://127.0.0.1:8000/product/1","name":"Show Product","description":"","method":"GET","body":{},"parameters":[],"headers":[],"authentication":{},"metaSortKey":-1624719005261,"isPrivate":false,"settingStoreCookies":true,"settingSendCookies":true,"settingDisableRenderRequestBody":false,"settingEncodeUrl":true,"settingRebuildPath":true,"settingFollowRedirects":"global","_type":"request"},{"_id":"env_78a6871750082dbbcd31ed699548802714fb38ba","parentId":"wrk_9a02bb9cbdc244628a679b016925eb11","modified":1624715432738,"created":1624715432738,"name":"Base Environment","data":{},"dataPropertyOrder":null,"color":null,"isPrivate":false,"metaSortKey":1624715432738,"_type":"environment"},{"_id":"jar_78a6871750082dbbcd31ed699548802714fb38ba","parentId":"wrk_9a02bb9cbdc244628a679b016925eb11","modified":1624715432739,"created":1624715432739,"name":"Default Jar","cookies":[],"_type":"cookie_jar"},{"_id":"spc_607d13e07a52435587026daf5b9883ca","parentId":"wrk_9a02bb9cbdc244628a679b016925eb11","modified":1624715432662,"created":1624715432662,"fileName":"Mozantech","contents":"","contentType":"yaml","_type":"api_spec"}]}